{
    "name": "Lyheang",
    "identifier": "@Lyheang1",
    "sourceURL": "",
    "apps": [
        {
            "name": "CarX Street - RCS",
            "bundleIdentifier": "com.carxtech.sr",
            "developerName": "RAK",
            "version": "0.5.0",
            "versionDate": "2022-09-04",
            "downloadURL": "https://archive.org/download/car-x-street-rcs-v-0.5.0/CarX%20Street%20-%20RCS_V0.5.0.ipa",
            "localizedDescription": "IGG & RCS DLG Tutorial Hack : @CarXStreetIOSChannel",
            "iconURL": "/image/CarXStreet.PNG",
            "tintColor": "FFC300",
            "size": 3.2e+9,
            "screenshotURLs": [
                "/image/CarXStreet.PNG"
            ]
        },
       
    ]
}
